swc_registry/__init__.py
swc_registry/get_entry_info.py
swc_registry/swc-definition.json
swc_registry-0.0.11.dist-info/LICENSE
swc_registry-0.0.11.dist-info/METADATA
swc_registry-0.0.11.dist-info/WHEEL
swc_registry-0.0.11.dist-info/top_level.txt
swc_registry-0.0.11.dist-info/RECORD
